{
  "fields": [
    { "type": "int", "id": "_id" },
    { "type": "text", "id": "ilce_adi" },
    { "type": "text", "id": "mahalle_adi" },
    { "type": "text", "id": "mahalle_koy_uavt" },
    { "type": "text", "id": "cok_agir_hasarli_bina_sayisi" },
    { "type": "text", "id": "agir_hasarli_bina_sayisi" },
    { "type": "text", "id": "orta_hasarli_bina_sayisi" },
    { "type": "text", "id": "hafif_hasarli_bina_sayisi" },
    { "type": "text", "id": "can_kaybi_sayisi" },
    { "type": "text", "id": "agir_yarali_sayisi" },
    { "type": "text", "id": "hastanede_tedavi_sayisi" },
    { "type": "text", "id": "hafif_yarali_sayisi" },
    { "type": "text", "id": "dogalgaz_boru_hasari" },
    { "type": "text", "id": "icme_suyu_boru_hasari" },
    { "type": "text", "id": "atik_su_boru_hasari" },
    { "type": "text", "id": "gecici_barinma" }
  ],
  "records": [
    [
      406,
      "EYÜP",
      "AĞAÇLI",
      "191741",
      "1",
      "4",
      "20",
      "52",
      "0",
      "0",
      "0",
      "0",
      "0",
      "0",
      "0",
      "23"
    ],
    [
      407,
      "EYÜP",
      "AKPINAR",
      "191743",
      "4",
      "10",
      "30",
      "65",
      "0",
      "0",
      "2",
      "3",
      "0",
      "0",
      "0",
      "48"
    ],
    [
      408,
      "EYÜP",
      "AKŞEMSETTİN",
      "40358",
      "4",
      "18",
      "107",
      "402",
      "3",
      "2",
      "14",
      "38",
      "0",
      "1",
      "1",
      "768"
    ],
    [
      409,
      "EYÜP",
      "ALİBEYKÖY",
      "40359",
      "19",
      "49",
      "203",
      "397",
      "9",
      "6",
      "26",
      "52",
      "0",
      "1",
      "1",
      "620"
    ],
    [
      410,
      "EYÜP",
      "ÇIRÇIR",
      "40360",
      "7",
      "26",
      "148",
      "452",
      "2",
      "1",
      "13",
      "30",
      "0",
      "0",
      "1",
      "701"
    ],
    [
      411,
      "EYÜP",
      "ÇİFTALAN",
      "191745",
      "1",
      "3",
      "7",
      "16",
      "0",
      "0",
      "0",
      "0",
      "0",
      "0",
      "0",
      "11"
    ],
    [
      412,
      "EYÜP",
      "DEFTERDAR",
      "40361",
      "29",
      "59",
      "207",
      "289",
      "15",
      "10",
      "37",
      "70",
      "0",
      "1",
      "1",
      "515"
    ],
    [
      413,
      "EYÜP",
      "DÜĞMECİLER",
      "40362",
      "14",
      "37",
      "183",
      "340",
      "14",
      "9",
      "39",
      "77",
      "0",
      "0",
      "1",
      "1229"
    ],
    [
      414,
      "EYÜP",
      "EMNİYETTEPE",
      "40363",
      "10",
      "25",
      "108",
      "240",
      "5",
      "3",
      "15",
      "30",
      "0",
      "0",
      "1",
      "436"
    ],
    [
      415,
      "EYÜP",
      "ESENTEPE",
      "40364",
      "10",
      "30",
      "137",
      "341",
      "5",
      "4",
      "17",
      "37",
      "0",
      "0",
      "1",
      "822"
    ],
    [
      416,
      "EYÜP",
      "GÖKTÜRK MERKEZ",
      "40379",
      "15",
      "64",
      "321",
      "745",
      "6",
      "1",
      "31",
      "76",
      "1",
      "1",
      "2",
      "1564"
    ],
    [
      417,
      "EYÜP",
      "GÜZELTEPE",
      "40366",
      "16",
      "43",
      "211",
      "532",
      "9",
      "6",
      "29",
      "62",
      "1",
      "1",
      "1",
      "1175"
    ],
    [
      418,
      "EYÜP",
      "IŞIKLAR",
      "191747",
      "1",
      "5",
      "22",
      "57",
      "0",
      "0",
      "0",
      "0",
      "0",
      "0",
      "0",
      "24"
    ],
    [
      419,
      "EYÜP",
      "İHSANİYE",
      "191749",
      "0",
      "2",
      "6",
      "14",
      "0",
      "0",
      "0",
      "0",
      "0",
      "0",
      "0",
      "9"
    ],
    [
      420,
      "EYÜP",
      "İSLAMBEY",
      "40367",
      "22",
      "54",
      "236",
      "482",
      "16",
      "11",
      "44",
      "87",
      "0",
      "0",
      "1",
      "844"
    ],
    [
      421,
      "EYÜP",
      "KARADOLAP",
      "40368",
      "12",
      "41",
      "197",
      "524",
      "5",
      "4",
      "21",
      "47",
      "0",
      "0",
      "1",
      "832"
    ],
    [
      422,
      "EYÜP",
      "MERKEZ",
      "40365",
      "26",
      "53",
      "187",
      "322",
      "15",
      "11",
      "43",
      "79",
      "1",
      "1",
      "1",
      "891"
    ],
    [
      423,
      "EYÜP",
      "MİMAR SİNAN",
      "40369",
      "5",
      "21",
      "101",
      "197",
      "1",
      "1",
      "5",
      "10",
      "0",
      "0",
      "1",
      "209"
    ],
    [
      424,
      "EYÜP",
      "MİTHATPAŞA",
      "40370",
      "11",
      "40",
      "180",
      "338",
      "2",
      "2",
      "8",
      "18",
      "1",
      "1",
      "1",
      "324"
    ],
    [
      425,
      "EYÜP",
      "NİŞANCI",
      "40371",
      "24",
      "66",
      "297",
      "492",
      "18",
      "13",
      "50",
      "98",
      "1",
      "1",
      "1",
      "1144"
    ],
    [
      426,
      "EYÜP",
      "ODAYERİ",
      "191751",
      "0",
      "2",
      "11",
      "27",
      "0",
      "0",
      "0",
      "0",
      "0",
      "0",
      "0",
      "10"
    ],
    [
      427,
      "EYÜP",
      "PİRİNÇÇİ",
      "191753",
      "3",
      "13",
      "65",
      "165",
      "0",
      "0",
      "1",
      "6",
      "0",
      "0",
      "0",
      "112"
    ],
    [
      428,
      "EYÜP",
      "RAMİ CUMA",
      "40372",
      "10",
      "26",
      "119",
      "244",
      "11",
      "7",
      "32",
      "61",
      "0",
      "0",
      "0",
      "911"
    ],
    [
      429,
      "EYÜP",
      "RAMİ YENİ",
      "40373",
      "15",
      "36",
      "157",
      "288",
      "11",
      "7",
      "31",
      "60",
      "0",
      "0",
      "1",
      "972"
    ],
    [
      430,
      "EYÜP",
      "SAKARYA",
      "40374",
      "6",
      "22",
      "101",
      "265",
      "3",
      "2",
      "11",
      "23",
      "0",
      "0",
      "0",
      "349"
    ],
    [
      431,
      "EYÜP",
      "SİLAHTARAĞA",
      "40375",
      "5",
      "17",
      "90",
      "240",
      "3",
      "2",
      "9",
      "20",
      "0",
      "0",
      "0",
      "342"
    ],
    [
      432,
      "EYÜP",
      "TOPÇULAR",
      "40376",
      "26",
      "62",
      "260",
      "366",
      "9",
      "5",
      "26",
      "50",
      "1",
      "1",
      "2",
      "455"
    ],
    [
      433,
      "EYÜP",
      "YEŞİLPINAR",
      "40378",
      "4",
      "13",
      "83",
      "345",
      "6",
      "3",
      "21",
      "46",
      "0",
      "0",
      "1",
      "727"
    ]
  ]
}
